[
    {
        "id": 1,
        "name": "Плюшевый мишка \"Teddies\" 30 см",
        "price": 1890,
        "category": "Мягкие игрушки",
        "description": "Этот очаровательный мишка станет лучшим другом для вашего малыша! Мягкий, как облачко, из высококачественного плюша, он безопасен даже для самых маленьких. Наполнитель – гипоаллергенный холлофайбер, который не скатывается и сохраняет форму. Мишка одет в вязаный шарфик, его можно стирать в деликатном режиме. Рекомендован для детей от 0 месяцев. Подарите своему ребёнку нежность и тепло!",
        "image": "69bebabcdaf54_1774107324.png",
        "age": "0+",
        "created_at": "2026-03-14 12:40:38"
    },
    {
        "id": 2,
        "name": "Заяц розовый (Aurora) 25 см",
        "price": 1450,
        "category": "Мягкие игрушки",
        "description": "Знаменитый розовый зайчик Aurora с длинными ушками покорит сердце любого ребёнка. Его шёрстка невероятно приятна на ощупь, а выразительные глазки-бусинки смотрят с любовью. Игрушка мягконабивная, устойчивая к деформации. Зайчик станет отличным подарком на день рождения или просто так, без повода!",
        "image": "69beb8540958c_1774106708.png",
        "age": "0+",
        "created_at": "2026-03-14 12:44:28"
    },
    {
        "id": 3,
        "name": "Собачка-подушка \"Hund\" 40 см",
        "price": 2100,
        "category": "Мягкие игрушки",
        "description": "Умопомрачительно мягкая такса-подушка! Она такая длинная и уютная, что на ней можно лежать, обнимать её или использовать как подушку для сна. Игрушка выполнена из велюра и набита гипоаллергенным материалом. Собачка безопасна, у неё нет мелких деталей. Дети обожают брать её с собой в постель – с ней так спокойно и сладко спится!",
        "image": "69b54a66d09a3_1773488742.jpg",
        "age": "0+",
        "created_at": "2026-03-14 12:45:42"
    },
    {
        "id": 4,
        "name": "Единорог радужный (Aurora) 35 см",
        "price": 2490,
        "category": "Мягкие игрушки",
        "description": "Настоящий сказочный единорог с мерцающей гривой и золотым рогом! Его радужная шёрстка переливается на свету, а мягкость зашкаливает. Это не просто игрушка, а верный спутник в мире фантазий. Единорог Aurora изготовлен из высококачественных материалов, безопасен для детей с рождения. Подарите дочке волшебство – она будет в восторге!",
        "image": "69b54ad425087_1773488852.jpg",
        "age": "0+",
        "created_at": "2026-03-14 12:47:32"
    },
    {
        "id": 5,
        "name": "Лисёнок \"Foxy\" с шарфиком 23 см",
        "price": 1250,
        "category": "Мягкие игрушки",
        "description": "Рыжий лисёнок Foxy, одетый в тёплый вязаный шарфик, такой трогательный и милый! Его пушистый хвостик и умные глазки никого не оставят равнодушным. Игрушка очень лёгкая, её удобно брать с собой на прогулку. Лисёнок станет любимцем вашего малыша и будет участвовать во всех играх.",
        "image": "69c23441221d4_1774335041.png",
        "age": "0+",
        "created_at": "2026-03-14 12:48:59"
    },
    {
        "id": 6,
        "name": "LEGO Duplo \"Супермаркет\" (10434)",
        "price": 10250,
        "category": "Конструкторы",
        "description": "Отправляйтесь за покупками вместе с Пеппой! Этот красочный набор LEGO Duplo включает фигурки Свинки Пеппы, Джорджа, мамы и папы Свин, а также множество аксессуаров: тележка, касса, продукты, морозильник. Игра развивает мелкую моторику, воображение и социальные навыки. Соберите свой супермаркет и устройте настоящее шоу!",
        "image": "69bebb44e5a2f_1774107460.png",
        "age": "3+",
        "created_at": "2026-03-14 13:15:59"
    },
    {
        "id": 7,
        "name": "LEGO City \"Полицейский участок\" (60316)",
        "price": 4990,
        "category": "Конструкторы",
        "description": "Внимание, в городе преступление! Набор LEGO City Полицейский участок – это всё, что нужно юному стражу порядка: само здание участка с диспетчерской, тюремная камера, полицейский автомобиль и мотоцикл, фигурки полицейских и преступника. Детали совместимы с другими наборами LEGO. Развивает логику, внимание и сюжетно-ролевую игру.",
        "image": "69bfec55a9e85_1774185557.png",
        "age": "5+",
        "created_at": "2026-03-14 13:16:49"
    },
    {
        "id": 8,
        "name": "Магнитный конструктор \"Magformers Wow\" (30 дет.)",
        "price": 5200,
        "category": "Конструкторы",
        "description": "Магия магнитов в действии! Magformers Wow – это не просто конструктор, а настоящий тренажёр для пространственного мышления. Из 30 магнитных деталей разных форм можно собрать всё что угодно: от домиков до фантастических животных. Детали легко соединяются и крепко держатся. Игра развивает логику, фантазию и мелкую моторику.",
        "image": "69bebd19e5318_1774107929.png",
        "age": "3+",
        "created_at": "2026-03-14 13:20:07"
    },
    {
        "id": 9,
        "name": "Конструктор \"Полесье\" Макси Строительная фирма (66 дет.)",
        "price": 1890,
        "category": "Конструкторы",
        "description": "Большой набор крупных блоков \"Полесье\" – идеальный старт для юного строителя! 66 ярких деталей позволят возвести невероятную строительную фирму. Детали совместимы с другими популярными брендами конструкторов. Материал – прочный безопасный пластик. Стройте, играйте, развивайтесь!",
        "image": "69bebd4493511_1774107972.png",
        "age": "3+",
        "created_at": "2026-03-14 13:24:41"
    },
    {
        "id": 10,
        "name": "Деревянный конструктор \"Томик\" (43 дет.)",
        "price": 890,
        "category": "Конструкторы",
        "description": "Экологичный деревянный конструктор от фабрики \"Томик\" – классика, проверенная поколениями. 43 цветных кубика, цилиндры, пирамидки из натурального дерева. Они приятно пахнут деревом и абсолютно безопасны. Конструктор знакомит малыша с формами и цветами, развивает моторику и координацию. Создайте свой сказочный городок!",
        "image": "69b553cc0bc90_1773491148.jpg",
        "age": "3+",
        "created_at": "2026-03-14 13:25:48"
    },
    {
        "id": 11,
        "name": "Hot Wheels \"Суперкары\" (набор 5 шт.)",
        "price": 1490,
        "category": "Машинки",
        "description": "Пять суперкрутых металлических машинок Hot Wheels в одном наборе! Каждая модель уникальна, с проработанными деталями и яркой раскраской. Масштаб 1:64. Машинки инерционные – откати назад и отпусти, они понесутся вперёд. Коллекционируй, устраивай гонки, создавай собственные трассы. Скорость и драйв ждут!",
        "image": "69bebd88895fa_1774108040.png",
        "age": "3+",
        "created_at": "2026-03-14 13:29:57"
    },
    {
        "id": 12,
        "name": "Пожарная машина с лестницей (Junior Motors) 1:48",
        "price": 950,
        "category": "Машинки",
        "description": "Настоящая пожарная машина \"Fire Liquidator Truck\" спешит на помощь! У неё вращается лестница, открываются дверцы, есть звуковые и световые эффекты (работает от батареек). Металлический корпус и прочные колёса позволяют играть где угодно. Машинка инерционная. Ребёнок почувствует себя отважным пожарным. Для детей от 3 лет. Спасай и побеждай!",
        "image": "69bfeddcce255_1774185948.png",
        "age": "3+",
        "created_at": "2026-03-14 13:31:48"
    },
    {
        "id": 13,
        "name": "Радиоуправляемый джип \"Hummer\"",
        "price": 3200,
        "category": "Машинки",
        "description": "Мощный внедорожник Hummer на радиоуправлении покорит любые бездорожье! Полный привод, резиновые шины с протектором, высокая проходимость. Скорость до 10 км\/ч. Управление на частоте 2.4 ГГц позволяет играть нескольким машинкам одновременно. Аккумулятор в комплекте. Подари ребёнку ощущение настоящей езды!",
        "image": "69bfee673a8c3_1774186087.png",
        "age": "5+",
        "created_at": "2026-03-14 13:33:18"
    },
    {
        "id": 14,
        "name": "Инёрционная машинка \"Спорткар\" 7 см",
        "price": 350,
        "category": "Машинки",
        "description": "Компактный металлический спорткар для быстрых гонок! Просто откати назад и отпусти – машинка молниеносно рванёт вперёд. Корпус из металла и пластика, яркая окраска. Идеально подходит для игр дома и на улице. Занимает мало места, можно брать с собой в путешествия.",
        "image": "69bfee92abe68_1774186130.png",
        "age": "3+",
        "created_at": "2026-03-14 13:34:31"
    },
    {
        "id": 15,
        "name": "Машинка \"Tesla Cybertruck\" радиоуправляемая (1:24)",
        "price": 2990,
        "category": "Машинки",
        "description": "Футуристический электропикап Tesla Cybertruck теперь в масштабе 1:24! Полностью радиоуправляемая модель с металлическим корпусом, резиновыми шинами и светящимися фарами. Управление на частоте 2.4 ГГц позволяет играть нескольким машинкам одновременно. Скорость до 8 км\/ч. Аккумулятор в комплекте, зарядка от USB. Игрушка развивает реакцию и интерес к современным технологиям.",
        "image": "69bfeeee1ad33_1774186222.png",
        "age": "5+",
        "created_at": "2026-03-14 13:38:20"
    },
    {
        "id": 16,
        "name": "Кукла Barbie \"Розовое платье\" 29 см",
        "price": 2490,
        "category": "Куклы",
        "description": "Элегантная Barbie в стильном розовом платье готова к выходу в свет! У куклы длинные ухоженные волосы, которые можно расчёсывать и укладывать в причёски. Руки и ноги подвижные, что позволяет принимать разные позы. В комплекте – модные туфельки. Барби развивает чувство стиля и социальные навыки.",
        "image": "69bff1598b911_1774186841.png",
        "age": "5+",
        "created_at": "2026-03-14 13:41:40"
    },
    {
        "id": 17,
        "name": "Малыш \"Baby Born\"",
        "price": 4990,
        "category": "Куклы",
        "description": "Интерактивный пупс Baby Born – почти настоящий малыш! Он умеет пить из бутылочки, плакать, смеяться, ходить на горшок и даже засыпать, если его покачать. Реагирует на прикосновения, издаёт более 10 звуков. Одет в милый костюмчик. В комплекте бутылочка, горшок, тарелка и ложка. Работает от батареек.",
        "image": "69b557def0792_1773492190.jpg",
        "age": "3+",
        "created_at": "2026-03-14 13:43:10"
    },
    {
        "id": 18,
        "name": "Кукла \"Анна\" Холодное сердце 30 см",
        "price": 1890,
        "category": "Куклы",
        "description": "Любимая принцесса Анна из мультфильма \"Холодное сердце\" теперь можно пригласить домой! Кукла в голубом платье с золотистой вышивкой, длинные рыжие волосы заплетены в косу. Одежда снимается, волосы можно расчёсывать. Руки и ноги подвижные. Игра с любимой героиней развивает воображение и эмоциональный интеллект.",
        "image": "69bff34027435_1774187328.png",
        "age": "5+",
        "created_at": "2026-03-14 13:46:03"
    },
    {
        "id": 19,
        "name": "Кукла-пупс \"Карапуз\" с ванночкой",
        "price": 1600,
        "category": "Куклы",
        "description": "Малыш Карапуз и его ванночка – всё для купания! Пупс в милом ползунках, в комплекте: ванночка, кувшинчик, мочалка, полотенце. Можно купать пупса, поливать его водичкой – он не боится воды. Игрушка развивает заботу и ответственность. Купание превращается в увлекательную игру!",
        "image": "69b558e3962f9_1773492451.jpg",
        "age": "3+",
        "created_at": "2026-03-14 13:47:31"
    },
    {
        "id": 20,
        "name": "LOL Surprise! Шарик-сюрприз \"Зимний стиль\"",
        "price": 1990,
        "category": "Куклы",
        "description": "Открой шарик и встреть новую подружку! В этом шарике LOL Surprise тебя ждёт куколка в зимнем образе. Внутри несколько слоёв с сюрпризами: одёжка, аксессуары, обувь, бутылочка-поилка, коллекционная наклейка и, конечно, сама куколка. Всего в коллекции 8 разных куколок — собери их всех! Игра развивает мелкую моторику, воображение и дарит радость открытия.",
        "image": "69bff30ae03a3_1774187274.png",
        "age": "5+",
        "created_at": "2026-03-14 13:50:49"
    },
    {
        "id": 21,
        "name": "Сортер \"Полесье\" Формы и цвета",
        "price": 650,
        "category": "Развивающие",
        "description": "Деревянный сортер \"Формы и цвета\" от Полесье – классическая обучающая игрушка. На яркой доске-основе расположены штырьки, на которые нужно нанизывать фигурки разной формы (круги, квадраты, треугольники) и цветов. Игра знакомит малыша с геометрическими фигурами, цветами, развивает мелкую моторику и логику.",
        "image": "69bff3823eec1_1774187394.png",
        "age": "3+",
        "created_at": "2026-03-14 13:53:11"
    },
    {
        "id": 22,
        "name": "Пирамидка-балансир \"Радуга\"",
        "price": 750,
        "category": "Развивающие",
        "description": "Удивительная деревянная пирамидка-балансир в форме радуги! Детали разного размера и цвета нужно уложить друг на друга так, чтобы конструкция не упала. Это отличная тренировка равновесия, глазомера и координации. Игрушка выполнена из натурального дерева, покрыта безопасными красками. Можно играть как в пирамидку, так и как в конструктор.",
        "image": "69c22ee2ad52c_1774333666.png",
        "age": "3+",
        "created_at": "2026-03-14 13:54:17"
    },
    {
        "id": 23,
        "name": "Умный сундучок Raduga Kids",
        "price": 2500,
        "category": "Развивающие",
        "description": "Многофункциональный развивающий сундучок от Raduga Kids – настоящая сокровищница знаний! В наборе: деревянные карточки с цифрами, буквами, животными, счётные палочки, мешочек, доска для рисования мелом. Играя, ребёнок учится считать, читать, различать цвета и формы. Всё упаковано в удобный деревянный ящичек.",
        "image": "69bff3ac61575_1774187436.png",
        "age": "3+",
        "created_at": "2026-03-14 13:55:15"
    },
    {
        "id": 24,
        "name": "Развивающий куб \"Активити\"",
        "price": 2400,
        "category": "Развивающие",
        "description": "Большой деревянный куб с 6 развивающими сторонами! Здесь и сортер, и лабиринт с шариками, и шестерёнки, и счёты, и доска для рисования. Малыш надолго увлечётся этой игрушкой, развивая логику, мелкую моторику и причинно-следственные связи. Куб устойчивый, безопасный.",
        "image": "69bff3f05fc17_1774187504.png",
        "age": "3+",
        "created_at": "2026-03-14 13:56:12"
    },
    {
        "id": 25,
        "name": "Пазл-20 maxi \"Волк и семеро козлят\"",
        "price": 105,
        "category": "Развивающие",
        "description": "Крупный пазл из 20 элементов по мотивам любимой сказки \"Волк и семеро козлят\". Детали большие, их удобно держать маленькими ручками. Собрав картинку, можно рассматривать героев и пересказывать сказку. Пазл развивает внимание, память и мелкую моторику.",
        "image": "69bff4f42c001_1774187764.png",
        "age": "3+",
        "created_at": "2026-03-14 14:01:10"
    },
    {
        "id": 26,
        "name": "Настольная игра \"Мемо\" (Животные)",
        "price": 490,
        "category": "Настольные игры",
        "description": "\"Мемо. Животные\" – увлекательная игра на тренировку памяти и внимания. В наборе 30 пар карточек с яркими изображениями зверей. Нужно находить одинаковые пары, запоминая их расположение. Игра развивает концентрацию и кругозор. Можно играть как одному, так и компанией.",
        "image": "69bff52986f7a_1774187817.png",
        "age": "5+",
        "created_at": "2026-03-14 14:03:48"
    },
    {
        "id": 27,
        "name": "Игра \"Равновесие\"",
        "price": 890,
        "category": "Настольные игры",
        "description": "Динамичная напольная игра \"Равновесие\" – отличный способ подвигаться и повеселиться всей семьёй! Игровое поле с кругами, рулетка показывает, на какой цвет поставить руку или ногу. Игроки должны удерживать равновесие, не падая. Развивает координацию, гибкость и вызывает море смеха.",
        "image": "69bff563defe8_1774187875.png",
        "age": "5+",
        "created_at": "2026-03-14 14:05:41"
    },
    {
        "id": 28,
        "name": "Домино \"Цвета\"",
        "price": 645,
        "category": "Настольные игры",
        "description": "Обучающее домино \"Цвета\" от ГЕОДОМ познакомит малыша с основными цветами. На карточках – яркие картинки, которые нужно соединять по принципу классического домино. Игра развивает внимательность, логическое мышление и расширяет словарный запас.",
        "image": "69b55d7fbddd7_1773493631.jpg",
        "age": "3+",
        "created_at": "2026-03-14 14:07:11"
    },
    {
        "id": 29,
        "name": "Игра-баланс \"Пингвины на льдине\"",
        "price": 950,
        "category": "Настольные игры",
        "description": "Весёлая игра на ловкость и равновесие! Нужно расставить пингвинов на вращающейся льдине так, чтобы они не упали. Игроки по очереди ставят фигурки. Кто уронит пингвина – проиграл. Игра развивает координацию и терпение. В наборе: льдина, 12 пингвинчиков, кубик.",
        "image": "69bff59145a7a_1774187921.png",
        "age": "5+",
        "created_at": "2026-03-14 14:09:23"
    },
    {
        "id": 30,
        "name": "Набор фокусов \"9 фокусов\" №4",
        "price": 430,
        "category": "Настольные игры",
        "description": "Юный иллюзионист будет в восторге! Набор \"9 фокусов\" содержит всё необходимое для первого шоу: исчезающие шарики, волшебная палочка, карты, монетки, кубики и подробная инструкция. Легко научиться, весело показывать друзьям! Развивает артистизм, мелкую моторику и уверенность в себе.",
        "image": "69bff67da796a_1774188157.png",
        "age": "7+",
        "created_at": "2026-03-14 14:10:03"
    },
    {
        "id": 31,
        "name": "Грызунок-прорезыватель \"Canpol\"",
        "price": 390,
        "category": "Для малышей",
        "description": "Мягкий силиконовый прорезыватель Canpol babies – идеальный помощник при прорезывании зубок. Рельефная поверхность массирует дёсны и облегчает боль. Удобная ручка позволяет малышу держать игрушку самостоятельно. Прорезыватель можно стерилизовать и мыть. Безопасный материал, не содержит бисфенол А.",
        "image": "69c2352167910_1774335265.png",
        "age": "0+",
        "created_at": "2026-03-14 14:12:20"
    },
    {
        "id": 32,
        "name": "Развивающий коврик \"Fisher-Price\"",
        "price": 3500,
        "category": "Для малышей",
        "description": "Музыкальный развивающий коврик Fisher-Price с дугами и подвесными игрушками станет любимым местом малыша. Дуги снимаются, игрушки можно менять местами. На коврике есть безопасное зеркальце, пищалки, шуршалки. Музыкальный блок проигрывает весёлые мелодии и звуки. Коврик мягкий, легко моется.",
        "image": "69bff6a5c62d5_1774188197.png",
        "age": "0+",
        "created_at": "2026-03-14 14:13:20"
    },
    {
        "id": 33,
        "name": "Погремушка \"Малышарики\"",
        "price": 159,
        "category": "Для малышей",
        "description": "Яркая погремушка с любимым героем \"Малышариков\"! Крепится на коляску, кроватку или автокресло. Игрушка имеет свою текстуру и звук: гремит, шуршит, пищит. Развивает слух, зрение и мелкую моторику.",
        "image": "69c22f13cf454_1774333715.png",
        "age": "0+",
        "created_at": "2026-03-14 14:15:49"
    },
    {
        "id": 34,
        "name": "Мягкие кубики \"Мякиши\" Три кота (6 шт.)",
        "price": 890,
        "category": "Для малышей",
        "description": "Знаменитые мягкие кубики \"Мякиши\" – безопасная альтернатива деревянным. Они лёгкие, приятные на ощупь, сшиты из разнофактурных тканей. Внутри – шуршащие и звенящие элементы. Кубики можно мять, кидать, строить из них башенки – они безопасны и не навредят малышу. Развивают тактильные ощущения и моторику.",
        "image": "69c2305c283ba_1774334044.png",
        "age": "0+",
        "created_at": "2026-03-14 14:16:57"
    },
    {
        "id": 35,
        "name": "Пингвинчик-качалка",
        "price": 1250,
        "category": "Для малышей",
        "description": "Очаровательная пирамидка-качалка в виде пингвина! Состоит из 7 деталей: фигурка пингвина и 6 разноцветных колечек. Детали можно складывать в стопку, и конструкция будет качаться, но не падать. Развивает координацию и чувство равновесия. Игрушка из натурального дерева и фетра, приятная на ощупь.",
        "image": "69c22fb0a9de5_1774333872.png",
        "age": "3+",
        "created_at": "2026-03-14 14:18:10"
    },
    {
        "id": 36,
        "name": "Планшет обучающий \"Умный малыш\"",
        "price": 1890,
        "category": "Электронные",
        "description": "Говорящий обучающий планшет – это 50+ заданий на русском языке! Ребёнок выучит буквы, цифры, названия животных, прослушает стихи и весёлые песенки. Есть кнопки-зверюшки, регулировка громкости. Работает от батареек. Игрушка развивает речь, память и музыкальный слух.",
        "image": "69c2301b64d33_1774333979.png",
        "age": "5+",
        "created_at": "2026-03-15 07:37:46"
    },
    {
        "id": 37,
        "name": "Робот \"Silverlit\"",
        "price": 2590,
        "category": "Электронные",
        "description": "Крутой робот-трансформер Silverlit! Он умеет ездить вперёд\/назад, поворачивать, и издавать звуки. Одним нажатием на пульте робот превращается в машину и обратно. Управление с пульта ДУ (радиус до 10 м). Это не просто игрушка, а настоящий друг для приключений!",
        "image": "69c230c06d1db_1774334144.png",
        "age": "5+",
        "created_at": "2026-03-15 07:39:25"
    },
    {
        "id": 38,
        "name": "Электронная азбука \"Знаток\" (плакат)",
        "price": 990,
        "category": "Электронные",
        "description": "Говорящий плакат \"Знаток\" – интерактивный способ выучить алфавит. Нажимай на букву – слышишь её название, слово и весёлый стишок. Есть режимы \"Экзамен\" и \"Игры\". Плакат вешается на стену, занимает мало места. Работает от батареек.",
        "image": "69c231c6960d8_1774334406.png",
        "age": "3+",
        "created_at": "2026-03-15 07:40:12"
    },
    {
        "id": 39,
        "name": "Детский микрофон \"Караоке\"",
        "price": 1290,
        "category": "Электронные",
        "description": "Настоящий микрофон с огоньками и эффектами! Можно петь встроенные песни, записывать свой голос и слушать его с изменённым звуком (эхо, робот). Есть разъём для подключения телефона или плеера – пойте любимые треки. Микрофон лёгкий, удобный для детской руки. Стань звездой сцены!",
        "image": "69c231f3e7c3a_1774334451.png",
        "age": "5+",
        "created_at": "2026-03-15 07:41:19"
    },
    {
        "id": 40,
        "name": "Интерактивная игрушка робот кошка \"Умный питомец\" 19 см",
        "price": 3200,
        "category": "Электронные",
        "description": "Познакомьтесь с очаровательным розовым котенком, который станет лучшим другом вашему ребенку! У него милый ошейник с погремушкой, а главная особенность – интерактивность. Котенок реагирует на звук хлопка и нежное поглаживание подбородка, что делает игру живой и увлекательной.",
        "image": "69c2323f0c564_1774334527.png",
        "age": "5+",
        "created_at": "2026-03-15 07:43:52"
    },
    {
        "id": 41,
        "name": "Мяч футбольный \"Select\" (размер 3)",
        "price": 1290,
        "category": "Спортивные",
        "description": "Качественный футбольный мяч Select размер 3 – идеальный для первых тренировок юного футболиста. Мяч сшит из износостойкой синтетической кожи, имеет резиновую камеру. Яркий дизайн, мягкий удар. Подходит для игр на траве и в зале.",
        "image": "69c2327d5295e_1774334589.png",
        "age": "5+",
        "created_at": "2026-03-15 07:47:17"
    },
    {
        "id": 42,
        "name": "Набор для бадминтона \"Demix\"",
        "price": 1490,
        "category": "Спортивные",
        "description": "Всё для активного отдыха на природе! Набор Demix включает две ракетки, два волана и сетку с опорами. Ракетки лёгкие, с удобной ручкой. Игра в бадминтон развивает реакцию, координацию и весело проводить время с семьёй и друзьями.",
        "image": "69c232b3ed163_1774334643.png",
        "age": "7+",
        "created_at": "2026-03-15 07:48:08"
    },
    {
        "id": 43,
        "name": "Кегли \"Играем вместе\" (6 шт.)",
        "price": 890,
        "category": "Спортивные",
        "description": "Набор ярких пластиковых кеглей с мячом от \"Играем вместе\". В наборе 6 кеглей и мяч. Кегли можно расставить как дома, так и на улице. Игра развивает меткость и координацию. Яркие цвета привлекают внимание. Устрой свой собственный боулинг!",
        "image": "69c232d1c3716_1774334673.png",
        "age": "3+",
        "created_at": "2026-03-15 07:48:54"
    },
    {
        "id": 44,
        "name": "Скакалка со счётчиком",
        "price": 390,
        "category": "Спортивные",
        "description": "Скакалка с электронным счётчиком прыжков поможет следить за тренировками. Длина регулируется под рост ребёнка. Ручки удобные, нескользящие. Счётчик показывает количество прыжков и время. Отличный способ привить любовь к спорту.",
        "image": "69c234bfdf38e_1774335167.png",
        "age": "5+",
        "created_at": "2026-03-15 07:49:47"
    },
    {
        "id": 45,
        "name": "Пикабол с мячом на резинке",
        "price": 350,
        "category": "Спортивные",
        "description": "Простая и захватывающая игра для одного или двоих! Ракетка соединена резинкой с мячом. Отбивай мяч ракеткой снова и снова, стараясь не уронить. Развивает ловкость, реакцию и координацию. Компактная, можно брать в дорогу.",
        "image": "69b656ed01fbe_1773557485.jpg",
        "age": "5+",
        "created_at": "2026-03-15 07:51:25"
    },
    {
        "id": 46,
        "name": "Набор для рисования \"Crayola\" (12 фломастеров)",
        "price": 590,
        "category": "Творчество",
        "description": "Знаменитые фломастеры Crayola смываются с рук и одежды! В наборе 12 ярких цветов. Фломастеры не высыхают надолго, даже если забыть закрыть колпачок. Рисование развивает фантазию и мелкую моторику.",
        "image": "69c2333ddd287_1774334781.png",
        "age": "3+",
        "created_at": "2026-03-15 07:53:42"
    },
    {
        "id": 47,
        "name": "Набор для мыловарения \"Фруктовое изобилие\"",
        "price": 890,
        "category": "Творчество",
        "description": "Увлекательный набор для создания мыла своими руками Фруктовое изобилие! В комплекте мыльная основа, формочки, ароматизаторы, красители, палочки для размешивания, подробная инструкция. Можно сделать 3-4 кусочка ароматного мыла. Развивает творческие способности и интерес к химии.",
        "image": "69c23361203eb_1774334817.png",
        "age": "7+",
        "created_at": "2026-03-15 07:55:46"
    },
    {
        "id": 48,
        "name": "Гравюра \"Животные\" с эффектом голографии",
        "price": 290,
        "category": "Творчество",
        "description": "Гравюра с голографическим эффектом – это увлекательное творчество для юного художника. С помощью специального штихеля нужно процарапать рисунок, и под слоем краски откроется сияющий фон. В наборе: основа для гравюры, штихель. Тренирует усидчивость и аккуратность.",
        "image": "69c234f9e4b1c_1774335225.png",
        "age": "5+",
        "created_at": "2026-03-15 07:57:10"
    },
    {
        "id": 49,
        "name": "Набор \"Украшаем подушку. Кошечка\"",
        "price": 1259,
        "category": "Творчество",
        "description": "Большой набор для создания мягкой подушки-кошечки без шитья! Более 320 деталей: лоскутки ткани разных цветов и фактур, заготовка подушки, элементы декора (глазки, носик), клей, подробная инструкция. Ребёнок сможет сам украсить подушку, развивая фантазию и дизайнерские навыки.",
        "image": "69c233e841508_1774334952.png",
        "age": "7+",
        "created_at": "2026-03-15 07:58:36"
    },
    {
        "id": 50,
        "name": "Набор для творчества \"Волшебные браслеты дружбы\"",
        "price": 890,
        "category": "Творчество",
        "description": "Этот набор откроет перед ребёнком мир увлекательного рукоделия. В комплекте всё необходимое для создания ярких фенечек и браслетов: 10 разноцветных ниток мулине высокого качества, бусины с буквами, сердечками и звёздочками из дерева и пластика, удобный станок для плетения, металлические замочки и колечки, пошаговая инструкция с более чем 10 схемами, а также разделитель для нитей и игла для бисера. Игра развивает мелкую моторику, координацию, творческое мышление, чувство стиля, усидчивость и аккуратность. Готовые браслеты можно дарить подружкам и одноклассницам как символ дружбы.",
        "image": "69c23418275c1_1774335000.png",
        "age": "7+",
        "created_at": "2026-03-15 08:02:11"
    }
]